{"link": "https://spb.hh.ru/vacancy/93089691?query=Python+django+flask&hhtmFrom=vacancy_search_list", "salary": "\u043e\u0442 300 000 \u20bd", "company": "Hyper AdTech", "city": "\u041c\u043e\u0441\u043a\u0432\u0430"}
{"link": "https://spb.hh.ru/vacancy/94112192?query=Python+django+flask&hhtmFrom=vacancy_search_list", "salary": "120 000 \u2013 160 000 \u20bd", "company": "PMP Tech", "city": "\u0421\u0430\u043d\u043a\u0442-\u041f\u0435\u0442\u0435\u0440\u0431\u0443\u0440\u0433"}
{"link": "https://spb.hh.ru/vacancy/92627503?query=Python+django+flask&hhtmFrom=vacancy_search_list", "salary": "\u0434\u043e 120 000 \u20bd", "company": null, "city": "\u041c\u043e\u0441\u043a\u0432\u0430, \u0412\u043e\u0440\u043e\u043d\u0446\u043e\u0432\u0441\u043a\u0430\u044f \u0438 \u0435\u0449\u0435..."}
{"link": "https://spb.hh.ru/vacancy/92761145?query=Python+django+flask&hhtmFrom=vacancy_search_list", "salary": "\u041d\u0435 \u0443\u043a\u0430\u0437\u0430\u043d\u0430", "company": "ITM-Space", "city": "\u041c\u043e\u0441\u043a\u0432\u0430"}
{"link": "https://spb.hh.ru/vacancy/93628858?query=Python+django+flask&hhtmFrom=vacancy_search_list", "salary": "\u043e\u0442 250 000 \u20bd", "company": "B.ART", "city": "\u041c\u043e\u0441\u043a\u0432\u0430"}
{"link": "https://spb.hh.ru/vacancy/93048944?query=Python+django+flask&hhtmFrom=vacancy_search_list", "salary": "250 000 \u2013 320 000 \u20bd", "company": "MIA Dev", "city": "\u041c\u043e\u0441\u043a\u0432\u0430"}
{"link": "https://spb.hh.ru/vacancy/92965237?query=Python+django+flask&hhtmFrom=vacancy_search_list", "salary": "\u041d\u0435 \u0443\u043a\u0430\u0437\u0430\u043d\u0430", "company": null, "city": "\u041c\u043e\u0441\u043a\u0432\u0430"}
{"link": "https://spb.hh.ru/vacancy/94107180?query=Python+django+flask&hhtmFrom=vacancy_search_list", "salary": "\u041d\u0435 \u0443\u043a\u0430\u0437\u0430\u043d\u0430", "company": null, "city": "\u0421\u0430\u043d\u043a\u0442-\u041f\u0435\u0442\u0435\u0440\u0431\u0443\u0440\u0433"}
{"link": "https://spb.hh.ru/vacancy/93474550?query=Python+django+flask&hhtmFrom=vacancy_search_list", "salary": "\u041d\u0435 \u0443\u043a\u0430\u0437\u0430\u043d\u0430", "company": "OneTwoTrip", "city": "\u041c\u043e\u0441\u043a\u0432\u0430"}
{"link": "https://spb.hh.ru/vacancy/93559599?query=Python+django+flask&hhtmFrom=vacancy_search_list", "salary": "350 000 \u2013 450 000 \u20bd", "company": "\u0422\u0440\u0438\u0430\u0444\u043b\u0430\u0439", "city": "\u041c\u043e\u0441\u043a\u0432\u0430, \u041a\u0443\u0437\u043d\u0435\u0446\u043a\u0438\u0439 \u043c\u043e\u0441\u0442"}
{"link": "https://spb.hh.ru/vacancy/91460286?query=Python+django+flask&hhtmFrom=vacancy_search_list", "salary": "\u041d\u0435 \u0443\u043a\u0430\u0437\u0430\u043d\u0430", "company": null, "city": "\u041c\u043e\u0441\u043a\u0432\u0430"}
{"link": "https://spb.hh.ru/vacancy/93809121?query=Python+django+flask&hhtmFrom=vacancy_search_list", "salary": "\u041d\u0435 \u0443\u043a\u0430\u0437\u0430\u043d\u0430", "company": "HuntIT", "city": "\u0421\u0430\u043d\u043a\u0442-\u041f\u0435\u0442\u0435\u0440\u0431\u0443\u0440\u0433"}
{"link": "https://spb.hh.ru/vacancy/93804537?query=Python+django+flask&hhtmFrom=vacancy_search_list", "salary": "\u041d\u0435 \u0443\u043a\u0430\u0437\u0430\u043d\u0430", "company": "Lesta Games", "city": "\u041c\u043e\u0441\u043a\u0432\u0430, \u0421\u0430\u0432\u0451\u043b\u043e\u0432\u0441\u043a\u0430\u044f \u0438 \u0435\u0449\u0435\u00a02\u00a0"}
{"link": "https://spb.hh.ru/vacancy/93238507?query=Python+django+flask&hhtmFrom=vacancy_search_list", "salary": "\u043e\u0442 150 000 \u20bd", "company": null, "city": "\u0421\u0430\u043d\u043a\u0442-\u041f\u0435\u0442\u0435\u0440\u0431\u0443\u0440\u0433"}
{"link": "https://spb.hh.ru/vacancy/94029854?query=Python+django+flask&hhtmFrom=vacancy_search_list", "salary": "\u041d\u0435 \u0443\u043a\u0430\u0437\u0430\u043d\u0430", "company": "BI.ZONE \u041d\u0430\u043f\u0440\u0430\u0432\u043b\u0435\u043d\u0438\u0435 \u0420\u0430\u0437\u0440\u0430\u0431\u043e\u0442\u043a\u0430", "city": "\u041c\u043e\u0441\u043a\u0432\u0430, \u0411\u0430\u0443\u043c\u0430\u043d\u0441\u043a\u0430\u044f \u0438 \u0435\u0449\u0435\u00a02\u00a0"}
{"link": "https://spb.hh.ru/vacancy/72687504?query=Python+django+flask&hhtmFrom=vacancy_search_list", "salary": "150 000 \u2013 200 000 \u20bd", "company": null, "city": "\u041c\u043e\u0441\u043a\u0432\u0430, \u0422\u0440\u0443\u0431\u043d\u0430\u044f \u0438 \u0435\u0449\u0435\u00a02\u00a0"}
{"link": "https://spb.hh.ru/vacancy/92547040?query=Python+django+flask&hhtmFrom=vacancy_search_list", "salary": "\u043e\u0442 70 000 \u20bd", "company": null, "city": "\u0421\u0430\u043d\u043a\u0442-\u041f\u0435\u0442\u0435\u0440\u0431\u0443\u0440\u0433"}
{"link": "https://spb.hh.ru/vacancy/92547113?query=Python+django+flask&hhtmFrom=vacancy_search_list", "salary": "\u043e\u0442 100 000 \u20bd", "company": null, "city": "\u0421\u0430\u043d\u043a\u0442-\u041f\u0435\u0442\u0435\u0440\u0431\u0443\u0440\u0433"}
{"link": "https://spb.hh.ru/vacancy/93157975?query=Python+django+flask&hhtmFrom=vacancy_search_list", "salary": "\u041d\u0435 \u0443\u043a\u0430\u0437\u0430\u043d\u0430", "company": "AldanDev", "city": "\u041c\u043e\u0441\u043a\u0432\u0430"}
{"link": "https://spb.hh.ru/vacancy/94032678?query=Python+django+flask&hhtmFrom=vacancy_search_list", "salary": "\u041d\u0435 \u0443\u043a\u0430\u0437\u0430\u043d\u0430", "company": "DSSL", "city": "\u041c\u043e\u0441\u043a\u0432\u0430"}
